database_automation/__init__.py
database_automation/mongo_crud.py
database_automation_ioklj-0.0.5.dist-info/LICENSE
database_automation_ioklj-0.0.5.dist-info/METADATA
database_automation_ioklj-0.0.5.dist-info/WHEEL
database_automation_ioklj-0.0.5.dist-info/top_level.txt
database_automation_ioklj-0.0.5.dist-info/RECORD
