Metadata-Version: 2.1
Name: database-automation-ioklj
Version: 0.0.5
Summary: A python package for connecting with any database.
Home-page: https://github.com/dasaditya1999/MongoDBConnection
Author: dasaditya1999
Author-email: adityanarayan.das1999@gmail.com
License: Apache License 2.0
Project-URL: Bug Tracker, https://github.com/dasaditya1999/MongoDBConnection/issues
Classifier: Programming Language :: Python :: 3.7
Classifier: Programming Language :: Python :: 3.8
Classifier: Programming Language :: Python :: 3.9
Classifier: Operating System :: OS Independent
Requires-Python: >=3.7
License-File: LICENSE
Requires-Dist: pymongo
Requires-Dist: pymongo[srv]
Requires-Dist: dnspython
Requires-Dist: pandas
Requires-Dist: numpy
Requires-Dist: ensure
Requires-Dist: pytest
Provides-Extra: testing
Requires-Dist: pytest >=7.1.3 ; extra == 'testing'
Requires-Dist: mypy >=0.971 ; extra == 'testing'
Requires-Dist: flake8 >=5.0.4 ; extra == 'testing'
Requires-Dist: tox >=3.25.1 ; extra == 'testing'
Requires-Dist: black >=22.8.0 ; extra == 'testing'
